USRVoiceConverter/VoiceConverter.py
USRVoiceConverter/__init__.py
USRVoiceConverter-1.0.0.dist-info/LICENSE
USRVoiceConverter-1.0.0.dist-info/METADATA
USRVoiceConverter-1.0.0.dist-info/WHEEL
USRVoiceConverter-1.0.0.dist-info/entry_points.txt
USRVoiceConverter-1.0.0.dist-info/top_level.txt
USRVoiceConverter-1.0.0.dist-info/RECORD
